<annotation><filename>DJI-00760-00002.jpg</filename><folder /><source><sourceImage /><sourceAnnotation>rubetools</sourceAnnotation></source><imagesize><nrows>1080</nrows><ncols>1920</ncols></imagesize><object><name>small_vehicle</name><deleted>0</deleted><verified>0</verified><occluded>no</occluded><date>2021-03-05 17:59:47.027384</date><id>0</id><parts><hasparts /><ispartof /></parts><polygon><pt><x>1323</x><y>573</y></pt><pt><x>1390</x><y>573</y></pt><pt><x>1390</x><y>604</y></pt><pt><x>1323</x><y>604</y></pt></polygon><attributes /></object><object><name>small_vehicle</name><deleted>0</deleted><verified>0</verified><occluded>no</occluded><date>2021-03-05 17:59:47.027398</date><id>1</id><parts><hasparts /><ispartof /></parts><polygon><pt><x>1305</x><y>521</y></pt><pt><x>1380</x><y>521</y></pt><pt><x>1380</x><y>556</y></pt><pt><x>1305</x><y>556</y></pt></polygon><attributes /></object><object><name>small_vehicle</name><deleted>0</deleted><verified>0</verified><occluded>no</occluded><date>2021-03-05 17:59:47.027406</date><id>2</id><parts><hasparts /><ispartof /></parts><polygon><pt><x>715</x><y>86</y></pt><pt><x>747</x><y>86</y></pt><pt><x>747</x><y>157</y></pt><pt><x>715</x><y>157</y></pt></polygon><attributes /></object><object><name>small_vehicle</name><deleted>0</deleted><verified>0</verified><occluded>no</occluded><date>2021-03-05 17:59:47.027414</date><id>3</id><parts><hasparts /><ispartof /></parts><polygon><pt><x>258</x><y>724</y></pt><pt><x>372</x><y>724</y></pt><pt><x>372</x><y>775</y></pt><pt><x>258</x><y>775</y></pt></polygon><attributes /></object><object><name>small_vehicle</name><deleted>0</deleted><verified>0</verified><occluded>no</occluded><date>2021-03-05 17:59:47.027422</date><id>4</id><parts><hasparts /><ispartof /></parts><polygon><pt><x>1788</x><y>389</y></pt><pt><x>1903</x><y>389</y></pt><pt><x>1903</x><y>430</y></pt><pt><x>1788</x><y>430</y></pt></polygon><attributes /></object><object><name>small_vehicle</name><deleted>0</deleted><verified>0</verified><occluded>no</occluded><date>2021-03-05 17:59:47.027431</date><id>5</id><parts><hasparts /><ispartof /></parts><polygon><pt><x>1284</x><y>466</y></pt><pt><x>1393</x><y>466</y></pt><pt><x>1393</x><y>506</y></pt><pt><x>1284</x><y>506</y></pt></polygon><attributes /></object><object><name>large_vehicle</name><deleted>0</deleted><verified>0</verified><occluded>no</occluded><date>2021-03-05 17:59:47.027439</date><id>6</id><parts><hasparts /><ispartof /></parts><polygon><pt><x>1400</x><y>465</y></pt><pt><x>1589</x><y>465</y></pt><pt><x>1589</x><y>526</y></pt><pt><x>1400</x><y>526</y></pt></polygon><attributes /></object><object><name>large_vehicle</name><deleted>0</deleted><verified>0</verified><occluded>no</occluded><date>2021-03-05 17:59:47.027447</date><id>7</id><parts><hasparts /><ispartof /></parts><polygon><pt><x>957</x><y>291</y></pt><pt><x>1003</x><y>291</y></pt><pt><x>1003</x><y>560</y></pt><pt><x>957</x><y>560</y></pt></polygon><attributes /></object><object><name>large_vehicle</name><deleted>0</deleted><verified>0</verified><occluded>no</occluded><date>2021-03-05 17:59:47.027455</date><id>8</id><parts><hasparts /><ispartof /></parts><polygon><pt><x>855</x><y>970</y></pt><pt><x>904</x><y>970</y></pt><pt><x>904</x><y>1078</y></pt><pt><x>855</x><y>1078</y></pt></polygon><attributes /></object><object><name>small_vehicle</name><deleted>0</deleted><verified>0</verified><occluded>no</occluded><date>2021-03-05 17:59:47.027463</date><id>9</id><parts><hasparts /><ispartof /></parts><polygon><pt><x>959</x><y>1015</y></pt><pt><x>990</x><y>1015</y></pt><pt><x>990</x><y>1078</y></pt><pt><x>959</x><y>1078</y></pt></polygon><attributes /></object><object><name>small_vehicle</name><deleted>0</deleted><verified>0</verified><occluded>no</occluded><date>2021-03-05 17:59:47.027470</date><id>10</id><parts><hasparts /><ispartof /></parts><polygon><pt><x>801</x><y>859</y></pt><pt><x>834</x><y>859</y></pt><pt><x>834</x><y>931</y></pt><pt><x>801</x><y>931</y></pt></polygon><attributes /></object><object><name>small_vehicle</name><deleted>0</deleted><verified>0</verified><occluded>no</occluded><date>2021-03-05 17:59:47.027503</date><id>11</id><parts><hasparts /><ispartof /></parts><polygon><pt><x>898</x><y>775</y></pt><pt><x>934</x><y>775</y></pt><pt><x>934</x><y>850</y></pt><pt><x>898</x><y>850</y></pt></polygon><attributes /></object><object><name>small_vehicle</name><deleted>0</deleted><verified>0</verified><occluded>no</occluded><date>2021-03-05 17:59:47.027512</date><id>12</id><parts><hasparts /><ispartof /></parts><polygon><pt><x>627</x><y>743</y></pt><pt><x>696</x><y>743</y></pt><pt><x>696</x><y>786</y></pt><pt><x>627</x><y>786</y></pt></polygon><attributes /></object><object><name>small_vehicle</name><deleted>0</deleted><verified>0</verified><occluded>no</occluded><date>2021-03-05 17:59:47.027520</date><id>13</id><parts><hasparts /><ispartof /></parts><polygon><pt><x>393</x><y>704</y></pt><pt><x>466</x><y>704</y></pt><pt><x>466</x><y>743</y></pt><pt><x>393</x><y>743</y></pt></polygon><attributes /></object><object><name>small_vehicle</name><deleted>0</deleted><verified>0</verified><occluded>no</occluded><date>2021-03-05 17:59:47.027528</date><id>14</id><parts><hasparts /><ispartof /></parts><polygon><pt><x>390</x><y>652</y></pt><pt><x>464</x><y>652</y></pt><pt><x>464</x><y>693</y></pt><pt><x>390</x><y>693</y></pt></polygon><attributes /></object><object><name>small_vehicle</name><deleted>0</deleted><verified>0</verified><occluded>no</occluded><date>2021-03-05 17:59:47.027536</date><id>15</id><parts><hasparts /><ispartof /></parts><polygon><pt><x>767</x><y>591</y></pt><pt><x>799</x><y>591</y></pt><pt><x>799</x><y>667</y></pt><pt><x>767</x><y>667</y></pt></polygon><attributes /></object><object><name>small_vehicle</name><deleted>0</deleted><verified>0</verified><occluded>no</occluded><date>2021-03-05 17:59:47.027543</date><id>16</id><parts><hasparts /><ispartof /></parts><polygon><pt><x>935</x><y>642</y></pt><pt><x>968</x><y>642</y></pt><pt><x>968</x><y>707</y></pt><pt><x>935</x><y>707</y></pt></polygon><attributes /></object><object><name>small_vehicle</name><deleted>0</deleted><verified>0</verified><occluded>no</occluded><date>2021-03-05 17:59:47.027551</date><id>17</id><parts><hasparts /><ispartof /></parts><polygon><pt><x>812</x><y>647</y></pt><pt><x>841</x><y>647</y></pt><pt><x>841</x><y>718</y></pt><pt><x>812</x><y>718</y></pt></polygon><attributes /></object><object><name>small_vehicle</name><deleted>0</deleted><verified>0</verified><occluded>no</occluded><date>2021-03-05 17:59:47.027559</date><id>18</id><parts><hasparts /><ispartof /></parts><polygon><pt><x>883</x><y>516</y></pt><pt><x>916</x><y>516</y></pt><pt><x>916</x><y>588</y></pt><pt><x>883</x><y>588</y></pt></polygon><attributes /></object><object><name>small_vehicle</name><deleted>0</deleted><verified>0</verified><occluded>no</occluded><date>2021-03-05 17:59:47.027567</date><id>19</id><parts><hasparts /><ispartof /></parts><polygon><pt><x>810</x><y>465</y></pt><pt><x>839</x><y>465</y></pt><pt><x>839</x><y>538</y></pt><pt><x>810</x><y>538</y></pt></polygon><attributes /></object><object><name>small_vehicle</name><deleted>0</deleted><verified>0</verified><occluded>no</occluded><date>2021-03-05 17:59:47.027574</date><id>20</id><parts><hasparts /><ispartof /></parts><polygon><pt><x>885</x><y>242</y></pt><pt><x>917</x><y>242</y></pt><pt><x>917</x><y>314</y></pt><pt><x>885</x><y>314</y></pt></polygon><attributes /></object><object><name>small_vehicle</name><deleted>0</deleted><verified>0</verified><occluded>no</occluded><date>2021-03-05 17:59:47.027582</date><id>21</id><parts><hasparts /><ispartof /></parts><polygon><pt><x>808</x><y>276</y></pt><pt><x>840</x><y>276</y></pt><pt><x>840</x><y>346</y></pt><pt><x>808</x><y>346</y></pt></polygon><attributes /></object><object><name>small_vehicle</name><deleted>0</deleted><verified>0</verified><occluded>no</occluded><date>2021-03-05 17:59:47.027590</date><id>22</id><parts><hasparts /><ispartof /></parts><polygon><pt><x>763</x><y>318</y></pt><pt><x>795</x><y>318</y></pt><pt><x>795</x><y>386</y></pt><pt><x>763</x><y>386</y></pt></polygon><attributes /></object><object><name>small_vehicle</name><deleted>0</deleted><verified>0</verified><occluded>no</occluded><date>2021-03-05 17:59:47.027598</date><id>23</id><parts><hasparts /><ispartof /></parts><polygon><pt><x>1877</x><y>543</y></pt><pt><x>1920</x><y>543</y></pt><pt><x>1920</x><y>576</y></pt><pt><x>1877</x><y>576</y></pt></polygon><attributes /></object><object><name>small_vehicle</name><deleted>0</deleted><verified>0</verified><occluded>no</occluded><date>2021-03-05 17:59:47.027605</date><id>24</id><parts><hasparts /><ispartof /></parts><polygon><pt><x>1769</x><y>571</y></pt><pt><x>1847</x><y>571</y></pt><pt><x>1847</x><y>609</y></pt><pt><x>1769</x><y>609</y></pt></polygon><attributes /></object><object><name>small_vehicle</name><deleted>0</deleted><verified>0</verified><occluded>no</occluded><date>2021-03-05 17:59:47.027613</date><id>25</id><parts><hasparts /><ispartof /></parts><polygon><pt><x>1695</x><y>513</y></pt><pt><x>1762</x><y>513</y></pt><pt><x>1762</x><y>544</y></pt><pt><x>1695</x><y>544</y></pt></polygon><attributes /></object><object><name>small_vehicle</name><deleted>0</deleted><verified>0</verified><occluded>no</occluded><date>2021-03-05 17:59:47.027621</date><id>26</id><parts><hasparts /><ispartof /></parts><polygon><pt><x>1604</x><y>502</y></pt><pt><x>1678</x><y>502</y></pt><pt><x>1678</x><y>541</y></pt><pt><x>1604</x><y>541</y></pt></polygon><attributes /></object><object><name>small_vehicle</name><deleted>0</deleted><verified>0</verified><occluded>no</occluded><date>2021-03-05 17:59:47.027630</date><id>27</id><parts><hasparts /><ispartof /></parts><polygon><pt><x>1560</x><y>548</y></pt><pt><x>1621</x><y>548</y></pt><pt><x>1621</x><y>582</y></pt><pt><x>1560</x><y>582</y></pt></polygon><attributes /></object><object><name>small_vehicle</name><deleted>0</deleted><verified>0</verified><occluded>no</occluded><date>2021-03-05 17:59:47.027638</date><id>28</id><parts><hasparts /><ispartof /></parts><polygon><pt><x>1427</x><y>529</y></pt><pt><x>1499</x><y>529</y></pt><pt><x>1499</x><y>562</y></pt><pt><x>1427</x><y>562</y></pt></polygon><attributes /></object><object><name>small_vehicle</name><deleted>0</deleted><verified>0</verified><occluded>no</occluded><date>2021-03-05 17:59:47.027647</date><id>29</id><parts><hasparts /><ispartof /></parts><polygon><pt><x>1414</x><y>579</y></pt><pt><x>1489</x><y>579</y></pt><pt><x>1489</x><y>612</y></pt><pt><x>1414</x><y>612</y></pt></polygon><attributes /></object></annotation>